medspellchecker/tool/abstract_bert_candidate_ranker.py
medspellchecker/tool/abstract_candidate_ranker.py
medspellchecker/tool/candidate_generator.py
medspellchecker/tool/candidate_word.py
medspellchecker/tool/distilbert_candidate_ranker.py
medspellchecker/tool/edit_distance.py
medspellchecker/tool/gpu_utils.py
medspellchecker/tool/medspellchecker.py
medspellchecker/tool/mistake_type.py
medspellchecker/tool/pre_post_processor.py
medspellchecker/tool/roberta_candidate_ranker.py
medspellchecker/tool/rubert_tiny2_candidate_ranker.py
medspellchecker/tool/rubioberta_candidate_ranker.py
medspellchecker/tool/rubioroberta_candidate_ranker.py
medspellchecker/tool/word.py
medspellchecker/tool/data/processed_lemmatized_all_dict.txt
medspellchecker-0.0.4.dist-info/LICENSE
medspellchecker-0.0.4.dist-info/METADATA
medspellchecker-0.0.4.dist-info/WHEEL
medspellchecker-0.0.4.dist-info/top_level.txt
medspellchecker-0.0.4.dist-info/RECORD
