Metadata-Version: 2.1
Name: medspellchecker
Version: 0.0.4
Summary: Fast and effective spellchecker for Russian medical texts
Home-page: https://github.com/DmitryPogrebnoy/MedSpellChecker
Author: Dmitry Pogrebnoy
Author-email: pogrebnoy.inc@gmail.com
License: Apache License 2.0
Project-URL: Bug Reports, https://github.com/DmitryPogrebnoy/MedSpellChecker/issues
Project-URL: Funding, https://donate.pypi.org
Keywords: spellchecker,nlp,medical,text correction
Classifier: Development Status :: 4 - Beta
Classifier: Intended Audience :: Developers
Classifier: Intended Audience :: Healthcare Industry
Classifier: Topic :: Software Development :: Libraries
Classifier: Topic :: Text Processing
Classifier: Topic :: Text Editors :: Word Processors
Classifier: License :: OSI Approved :: Apache Software License
Classifier: Programming Language :: Python
Classifier: Environment :: GPU :: NVIDIA CUDA
Requires-Python: >=3.9
License-File: LICENSE
Requires-Dist: pymorphy2 (>=0.9.1)
Requires-Dist: torch (>=1.11.0)
Requires-Dist: numpy (>=1.22)
Requires-Dist: scipy (>=1.7.3)
Requires-Dist: tqdm (>=4.62.3)
Requires-Dist: nltk (>=3.6.7)
Requires-Dist: editdistpy (>=0.1.3)
Requires-Dist: accelerate (>=0.12.0)
Requires-Dist: transformers (>=4.22.2)
Requires-Dist: sacremoses (>=0.0.49)
Requires-Dist: pynvml (>=11.4.1)
